outlier/__init__.py
outlier/i_outlier/IQR.py
outlier/i_outlier/Zscore.py
outlier/i_outlier/__init__.py
outlier/outlierGroup/__init__.py
outlier/outlierGroup/binning.py
outlier/outlierTech/__init__.py
outlier/outlierTech/remove.py
outlier/outlierTech/replace.py
outlier/outlierTech/winsorization/__init__.py
outlier/outlierTech/winsorization/adaptive.py
outlier/outlierTech/winsorization/standard.py
outlier_library-0.1.2.dist-info/LICENSE
outlier_library-0.1.2.dist-info/METADATA
outlier_library-0.1.2.dist-info/WHEEL
outlier_library-0.1.2.dist-info/top_level.txt
outlier_library-0.1.2.dist-info/RECORD
